DSAinPython/README.md
DSAinPython/__init__.py
DSAinPython/tempCodeRunnerFile.py
DSAinPython/LinkedList/CircularLL.py
DSAinPython/LinkedList/DoublyLL.py
DSAinPython/LinkedList/SinglyLL.py
DSAinPython/Queue/ArrDEQueue.py
DSAinPython/Queue/ArrQueue.py
DSAinPython/Queue/LLDEQueue.py
DSAinPython/Queue/LLQueue.py
DSAinPython/Searching/BinarySearchIter.py
DSAinPython/Searching/BinarySearchRec.py
DSAinPython/Searching/LinearSearch.py
DSAinPython/Searching/__init__.py
DSAinPython/Sorting/BubbleSort.py
DSAinPython/Sorting/CountSort.py
DSAinPython/Sorting/InsertionSort.py
DSAinPython/Sorting/MergeSort.py
DSAinPython/Sorting/QuickSort.py
DSAinPython/Sorting/RadixSort.py
DSAinPython/Sorting/SelectionSort.py
DSAinPython/Sorting/ShellSort.py
DSAinPython/Stack/ArrStack.py
DSAinPython/Stack/LLStack.py
DSAinPython-0.0.5.dist-info/LICENSE.txt
DSAinPython-0.0.5.dist-info/METADATA
DSAinPython-0.0.5.dist-info/WHEEL
DSAinPython-0.0.5.dist-info/top_level.txt
DSAinPython-0.0.5.dist-info/RECORD
