Metadata-Version: 2.1
Name: DSAinPython
Version: 0.0.5
Summary: This Package contains Data Structures and Algorithms
Home-page: https://github.com/Armaan-268/DSA_in_Python
Author: Armaan Chauhan
Author-email: armaanchauhan268@gmail.com
License: MIT
Keywords: datastructures,algorithms
Platform: UNKNOWN
